bmcgo/__init__.py
bmcgo/bmcgo.py
bmcgo/bmcgo_config.py
bmcgo/errors.py
bmcgo/frame.py
bmcgo/logger.py
bmcgo/misc.py
bmcgo/worker.py
bmcgo/cli/__init__.py
bmcgo/cli/cli.py
bmcgo/cli/config.conan2.yaml
bmcgo/cli/config.yaml
bmcgo/codegen/__init__.py
bmcgo/codegen/c/__init__.py
bmcgo/codegen/c/annotation.py
bmcgo/codegen/c/argument.py
bmcgo/codegen/c/codegen.py
bmcgo/codegen/c/comment.py
bmcgo/codegen/c/ctype_defination.py
bmcgo/codegen/c/helper.py
bmcgo/codegen/c/interface.py
bmcgo/codegen/c/method.py
bmcgo/codegen/c/property.py
bmcgo/codegen/c/renderer.py
bmcgo/codegen/c/signal.py
bmcgo/codegen/c/template/client.c.mako
bmcgo/codegen/c/template/client.h.mako
bmcgo/codegen/c/template/interface.c.mako
bmcgo/codegen/c/template/interface.introspect.xml.mako
bmcgo/codegen/c/template/micro_component.c.mako
bmcgo/codegen/c/template/public.c.mako
bmcgo/codegen/c/template/public.h.mako
bmcgo/codegen/c/template/server.c.mako
bmcgo/codegen/c/template/server.h.mako
bmcgo/codegen/lua/.lua-format
bmcgo/codegen/lua/Makefile
bmcgo/codegen/lua/__init__.py
bmcgo/codegen/lua/codegen.py
bmcgo/codegen/lua/proto/Makefile
bmcgo/codegen/lua/proto/ipmi_types.proto
bmcgo/codegen/lua/proto/types.proto
bmcgo/codegen/lua/script/base.py
bmcgo/codegen/lua/script/check_intfs.py
bmcgo/codegen/lua/script/factory.py
bmcgo/codegen/lua/script/gen_db_json.py
bmcgo/codegen/lua/script/gen_depends.py
bmcgo/codegen/lua/script/gen_entry.py
bmcgo/codegen/lua/script/gen_feature_json.py
bmcgo/codegen/lua/script/gen_historical_local_db_json.py
bmcgo/codegen/lua/script/gen_intf_json.py
bmcgo/codegen/lua/script/gen_intf_rpc_json.py
bmcgo/codegen/lua/script/gen_ipmi_json.py
bmcgo/codegen/lua/script/gen_mdb_json.py
bmcgo/codegen/lua/script/gen_rpc_msg_json.py
bmcgo/codegen/lua/script/gen_schema.py
bmcgo/codegen/lua/script/ipmi_types_pb2.py
bmcgo/codegen/lua/script/lua_format.py
bmcgo/codegen/lua/script/mdb_register.py
bmcgo/codegen/lua/script/mds_util.py
bmcgo/codegen/lua/script/merge_model.py
openubmc_bingo-0.6.122.dist-info/METADATA
openubmc_bingo-0.6.122.dist-info/WHEEL
openubmc_bingo-0.6.122.dist-info/entry_points.txt
openubmc_bingo-0.6.122.dist-info/top_level.txt
openubmc_bingo-0.6.122.dist-info/RECORD
