Metadata-Version: 2.1
Name: openubmc-bingo
Version: 0.6.122
Summary: Tools provided by openubmc
Home-page: https://openubmc.cn
Classifier: Programming Language :: Python :: 3
Classifier: License :: OSI Approved :: Mulan Permissive Software License v2 (MulanPSL-2.0)
Classifier: Operating System :: OS Independent
Requires-Dist: conan
Requires-Dist: cryptography <=42.0.7
Requires-Dist: dbus-next
Requires-Dist: dbus-python
Requires-Dist: ecdsa
Requires-Dist: gitpython
Requires-Dist: inflection
Requires-Dist: json5
Requires-Dist: jsonref
Requires-Dist: jsonschema
Requires-Dist: launchpadlib
Requires-Dist: mako
Requires-Dist: meson
Requires-Dist: node-semver ==0.6.1
Requires-Dist: paramiko <4.0.0
Requires-Dist: protobuf ==3.19.1
Requires-Dist: psutil
Requires-Dist: pyecharts
Requires-Dist: pyinstaller
Requires-Dist: pyopenssl <=24.1.0,>=23.2.0
Requires-Dist: pysftp
Requires-Dist: pyyaml-include
Requires-Dist: robotframework
Requires-Dist: tqdm ==4.67.1
Requires-Dist: typeguard ==2.13.3
